pesc/__init__.py
pesc/client.py
pesc/exceptions.py
pesc/tests.py
pesc-0.1.dist-info/METADATA
pesc-0.1.dist-info/RECORD
pesc-0.1.dist-info/WHEEL
pesc-0.1.dist-info/top_level.txt
